MANIFEST.in
setup.py
wordninja.py
wordninja_words.txt.gz
wordninja.egg-info/PKG-INFO
wordninja.egg-info/SOURCES.txt
wordninja.egg-info/dependency_links.txt
wordninja.egg-info/top_level.txt