Metadata-Version: 1.0
Name: wordninja
Version: 0.1.2
Summary: Probabilistically split concatenated words using NLP based on English Wikipedia uni-gram frequencies.
Home-page: https://github.com/keredson/wordninja
Author: Derek Anderson
Author-email: public@kered.org
License: UNKNOWN
Platform: UNKNOWN
